{
  "db_name": "PostgreSQL",
  "query": "\n        SELECT id, room_id, author_id, symbol, side, note, created_at\n        FROM alerts WHERE room_id = $1\n        ORDER BY created_at DESC LIMIT $2\n        ",
  "describe": {
    "columns": [
      {
        "ordinal": 0,
        "name": "id",
        "type_info": "Uuid",
        "origin": {
          "Table": {
            "table": "alerts",
            "name": "id"
          }
        }
      },
      {
        "ordinal": 1,
        "name": "room_id",
        "type_info": "Uuid",
        "origin": {
          "Table": {
            "table": "alerts",
            "name": "room_id"
          }
        }
      },
      {
        "ordinal": 2,
        "name": "author_id",
        "type_info": "Uuid",
        "origin": {
          "Table": {
            "table": "alerts",
            "name": "author_id"
          }
        }
      },
      {
        "ordinal": 3,
        "name": "symbol",
        "type_info": "Text",
        "origin": {
          "Table": {
            "table": "alerts",
            "name": "symbol"
          }
        }
      },
      {
        "ordinal": 4,
        "name": "side",
        "type_info": "Text",
        "origin": {
          "Table": {
            "table": "alerts",
            "name": "side"
          }
        }
      },
      {
        "ordinal": 5,
        "name": "note",
        "type_info": "Text",
        "origin": {
          "Table": {
            "table": "alerts",
            "name": "note"
          }
        }
      },
      {
        "ordinal": 6,
        "name": "created_at",
        "type_info": "Timestamptz",
        "origin": {
          "Table": {
            "table": "alerts",
            "name": "created_at"
          }
        }
      }
    ],
    "parameters": {
      "Left": [
        "Uuid",
        "Int8"
      ]
    },
    "nullable": [
      false,
      false,
      false,
      false,
      false,
      true,
      false
    ]
  },
  "hash": "b84e2606661d583150eaed5852e0df5936e2543996665e07889b657b2d6d955c"
}
